{
    "productId": "662a7dfd5ebf51570cec8066",
    "reviews": [
        {
          "name": "Rchap",
          "rating": 5,
          "subject": "Durable",
          "comment": "Fit great. Very durable. Big fan of the phone pocket",
          "datePosted": "01 Apr 2022"
        },
        {
          "name": "BoKnows",
          "rating": 5,
          "subject": "Perfect Fit",
          "comment": "Good quality and design, will buy again",
          "datePosted": "25 Apr 2023"
        },
        {
          "name": "Cabfog1957",
          "rating": 5,
          "subject": "Comfortable and excellent fabrics",
          "comment": "Comfortable with high quality fabrics. Delivery time was fast and easy",
          "datePosted": "04 Mar 2024"
        }
      ]
}